{
  "_comment": "N1 Phase 8-C: 渉 渋 渓 渚 渥 渦 湧 源 溝 滅 滉 滋 滑 滝 滞 漂 漆",
  "fills": {
    "渉": [
      { "readingRef": "ショウ", "word": "交渉", "wordReading": "こうしょう", "meaningsKo": ["교섭"], "examples": [] },
      { "readingRef": "ショウ", "word": "干渉", "wordReading": "かんしょう", "meaningsKo": ["간섭"], "examples": [] },
      { "readingRef": "ショウ", "word": "渉外", "wordReading": "しょうがい", "meaningsKo": ["섭외"], "examples": [] }
    ],
    "渋": [
      { "readingRef": "ジュウ", "word": "渋滞", "wordReading": "じゅうたい", "meaningsKo": ["정체", "교통체증"], "examples": [] },
      { "readingRef": "しぶい", "word": "渋い", "wordReading": "しぶい", "meaningsKo": ["떫다", "수수하다"], "examples": [] },
      { "readingRef": "ジュウ", "word": "苦渋", "wordReading": "くじゅう", "meaningsKo": ["고뇌", "고심"], "examples": [] }
    ],
    "渓": [
      { "readingRef": "ケイ", "word": "渓谷", "wordReading": "けいこく", "meaningsKo": ["계곡"], "examples": [] },
      { "readingRef": "ケイ", "word": "渓流", "wordReading": "けいりゅう", "meaningsKo": ["계류"], "examples": [] }
    ],
    "渚": [
      { "readingRef": "なぎさ", "word": "渚", "wordReading": "なぎさ", "meaningsKo": ["물가", "바닷가"], "examples": [] }
    ],
    "渥": [
      { "readingRef": "アク", "word": "渥恩", "wordReading": "あくおん", "meaningsKo": ["깊은 은혜"], "examples": [] }
    ],
    "渦": [
      { "readingRef": "うず", "word": "渦", "wordReading": "うず", "meaningsKo": ["소용돌이"], "examples": [] },
      { "readingRef": "うず", "word": "渦巻き", "wordReading": "うずまき", "meaningsKo": ["소용돌이"], "examples": [] }
    ],
    "湧": [
      { "readingRef": "わく", "word": "湧く", "wordReading": "わく", "meaningsKo": ["솟다", "솟아나다"], "examples": [] },
      { "readingRef": "ユウ", "word": "湧水", "wordReading": "ゆうすい", "meaningsKo": ["용수", "솟는 물"], "examples": [] }
    ],
    "源": [
      { "readingRef": "みなもと", "word": "源", "wordReading": "みなもと", "meaningsKo": ["근원", "원천"], "examples": [] },
      { "readingRef": "ゲン", "word": "資源", "wordReading": "しげん", "meaningsKo": ["자원"], "examples": [] },
      { "readingRef": "ゲン", "word": "電源", "wordReading": "でんげん", "meaningsKo": ["전원"], "examples": [] }
    ],
    "溝": [
      { "readingRef": "みぞ", "word": "溝", "wordReading": "みぞ", "meaningsKo": ["도랑", "홈"], "examples": [] },
      { "readingRef": "コウ", "word": "排水溝", "wordReading": "はいすいこう", "meaningsKo": ["배수구"], "examples": [] }
    ],
    "滅": [
      { "readingRef": "メツ", "word": "滅亡", "wordReading": "めつぼう", "meaningsKo": ["멸망"], "examples": [] },
      { "readingRef": "ほろびる", "word": "滅びる", "wordReading": "ほろびる", "meaningsKo": ["멸망하다"], "examples": [] },
      { "readingRef": "メツ", "word": "絶滅", "wordReading": "ぜつめつ", "meaningsKo": ["절멸", "멸종"], "examples": [] }
    ],
    "滉": [
      { "readingRef": "コウ", "word": "滉漾", "wordReading": "こうよう", "meaningsKo": ["넓고 깊은 모양"], "examples": [] }
    ],
    "滋": [
      { "readingRef": "ジ", "word": "滋養", "wordReading": "じよう", "meaningsKo": ["자양", "영양"], "examples": [] },
      { "readingRef": "ジ", "word": "滋賀", "wordReading": "しが", "meaningsKo": ["시가(지명)"], "examples": [] }
    ],
    "滑": [
      { "readingRef": "すべる", "word": "滑る", "wordReading": "すべる", "meaningsKo": ["미끄러지다"], "examples": [] },
      { "readingRef": "なめらか", "word": "滑らか", "wordReading": "なめらか", "meaningsKo": ["매끄러움"], "examples": [] },
      { "readingRef": "カツ", "word": "円滑", "wordReading": "えんかつ", "meaningsKo": ["원활"], "examples": [] }
    ],
    "滝": [
      { "readingRef": "たき", "word": "滝", "wordReading": "たき", "meaningsKo": ["폭포"], "examples": [] }
    ],
    "滞": [
      { "readingRef": "タイ", "word": "停滞", "wordReading": "ていたい", "meaningsKo": ["정체"], "examples": [] },
      { "readingRef": "とどこおる", "word": "滞る", "wordReading": "とどこおる", "meaningsKo": ["밀리다", "지체되다"], "examples": [] },
      { "readingRef": "タイ", "word": "滞在", "wordReading": "たいざい", "meaningsKo": ["체재", "체류"], "examples": [] }
    ],
    "漂": [
      { "readingRef": "ヒョウ", "word": "漂流", "wordReading": "ひょうりゅう", "meaningsKo": ["표류"], "examples": [] },
      { "readingRef": "ただよう", "word": "漂う", "wordReading": "ただよう", "meaningsKo": ["떠다니다", "감돌다"], "examples": [] },
      { "readingRef": "ヒョウ", "word": "漂白", "wordReading": "ひょうはく", "meaningsKo": ["표백"], "examples": [] }
    ],
    "漆": [
      { "readingRef": "うるし", "word": "漆", "wordReading": "うるし", "meaningsKo": ["옻", "옻칠"], "examples": [] },
      { "readingRef": "シツ", "word": "漆器", "wordReading": "しっき", "meaningsKo": ["칠기"], "examples": [] }
    ]
  }
}
