{
  "_comment": "N1 Examples Phase 11-D: 赴 趣 距 跳 践 踏 躍 軌 軸 較 載 輔 輝 輩 轄 辰 辱",
  "fills": {
    "赴/赴く": [{ "sentence": "{戦地|せんち}に{{赴いた}}。", "sentenceTranslationKo": "전쟁터에 향했다." }],
    "赴/赴任": [{ "sentence": "{父|ちち}は{大阪|おおさか}に{{赴任}}した。", "sentenceTranslationKo": "아버지는 오사카에 부임했다." }],
    "趣/趣味": [{ "sentence": "{彼|かれ}の{{趣味}}は{読書|どくしょ}だ。", "sentenceTranslationKo": "그의 취미는 독서이다." }],
    "趣/趣": [{ "sentence": "{この|この}{庭|にわ}には{{趣}}がある。", "sentenceTranslationKo": "이 정원에는 정취가 있다." }],
    "趣/趣旨": [{ "sentence": "{会議|かいぎ}の{{趣旨}}を{理解|りかい}した。", "sentenceTranslationKo": "회의의 취지를 이해했다." }],
    "距/距離": [{ "sentence": "{駅|えき}までの{{距離}}を{測|はか}った。", "sentenceTranslationKo": "역까지의 거리를 측정했다." }],
    "跳/跳ぶ": [{ "sentence": "{選手|せんしゅ}が{高|たか}く{{跳んだ}}。", "sentenceTranslationKo": "선수가 높이 뛰었다." }],
    "跳/跳ねる": [{ "sentence": "{ウサギ|うさぎ}が{{跳ねて}}いる。", "sentenceTranslationKo": "토끼가 뛰어오르고 있다." }],
    "跳/跳躍": [{ "sentence": "{陸上|りくじょう}{競技|きょうぎ}の{{跳躍}}{種目|しゅもく}に{出場|しゅつじょう}した。", "sentenceTranslationKo": "육상 경기의 도약 종목에 출전했다." }],
    "践/実践": [{ "sentence": "{学|まな}んだことを{{実践}}する。", "sentenceTranslationKo": "배운 것을 실천한다." }],
    "踏/踏む": [{ "sentence": "{ブレーキ|ぶれーき}を{{踏んだ}}。", "sentenceTranslationKo": "브레이크를 밟았다." }],
    "踏/踏襲": [{ "sentence": "{先代|せんだい}の{方針|ほうしん}を{{踏襲}}した。", "sentenceTranslationKo": "선대의 방침을 답습했다." }],
    "踏/雑踏": [{ "sentence": "{駅|えき}の{{雑踏}}に{紛|まぎ}れた。", "sentenceTranslationKo": "역의 혼잡에 묻혔다." }],
    "躍/躍る": [{ "sentence": "{心|こころ}が{{躍る}}{ような|ような}{知|し}らせだ。", "sentenceTranslationKo": "가슴이 뛰는 듯한 소식이다." }],
    "躍/活躍": [{ "sentence": "{彼|かれ}は{世界|せかい}で{{活躍}}している。", "sentenceTranslationKo": "그는 세계에서 활약하고 있다." }],
    "躍/飛躍": [{ "sentence": "{彼|かれ}は{大|おお}きな{{飛躍}}を{遂|と}げた。", "sentenceTranslationKo": "그는 큰 비약을 이루었다." }],
    "軌/軌道": [{ "sentence": "{計画|けいかく}が{{軌道}}に{乗|の}った。", "sentenceTranslationKo": "계획이 궤도에 올랐다." }],
    "軌/軌跡": [{ "sentence": "{彼|かれ}の{人生|じんせい}の{{軌跡}}を{追|お}う。", "sentenceTranslationKo": "그의 인생 궤적을 따라간다." }],
    "軸/軸": [{ "sentence": "{地球|ちきゅう}は{{軸}}を{中心|ちゅうしん}に{回転|かいてん}する。", "sentenceTranslationKo": "지구는 축을 중심으로 회전한다." }],
    "軸/枢軸": [{ "sentence": "{第二次|だいにじ}{世界|せかい}{大戦|たいせん}で{{枢軸}}{国|こく}が{敗|やぶ}れた。", "sentenceTranslationKo": "제2차 세계대전에서 추축국이 패배했다." }],
    "較/比較": [{ "sentence": "{二|に}つの{案|あん}を{{比較}}した。", "sentenceTranslationKo": "두 안을 비교했다." }],
    "較/較べる": [{ "sentence": "{兄|あに}と{{較べて}}{背|せ}が{低|ひく}い。", "sentenceTranslationKo": "형과 비교해 키가 작다." }],
    "載/載せる": [{ "sentence": "{記事|きじ}を{新聞|しんぶん}に{{載せた}}。", "sentenceTranslationKo": "기사를 신문에 실었다." }],
    "載/掲載": [{ "sentence": "{雑誌|ざっし}に{{掲載}}された。", "sentenceTranslationKo": "잡지에 게재됐다." }],
    "載/記載": [{ "sentence": "{書類|しょるい}に{{記載}}した。", "sentenceTranslationKo": "서류에 기재했다." }],
    "輔/輔佐": [{ "sentence": "{彼|かれ}は{社長|しゃちょう}を{{輔佐}}している。", "sentenceTranslationKo": "그는 사장을 보좌하고 있다." }],
    "輝/輝く": [{ "sentence": "{星|ほし}が{{輝いて}}いる。", "sentenceTranslationKo": "별이 빛나고 있다." }],
    "輝/光輝": [{ "sentence": "{彼|かれ}は{{光輝}}{ある|ある}{経歴|けいれき}を{持|も}つ。", "sentenceTranslationKo": "그는 광휘로운 경력을 가진다." }],
    "輩/先輩": [{ "sentence": "{部活|ぶかつ}の{{先輩}}に{相談|そうだん}した。", "sentenceTranslationKo": "동아리 선배에게 상담했다." }],
    "輩/後輩": [{ "sentence": "{{後輩}}を{指導|しどう}する。", "sentenceTranslationKo": "후배를 지도한다." }],
    "輩/輩出": [{ "sentence": "{この|この}{大学|だいがく}は{多|おお}くの{偉人|いじん}を{{輩出}}した。", "sentenceTranslationKo": "이 대학은 많은 위인을 배출했다." }],
    "轄/管轄": [{ "sentence": "{この|この}{地域|ちいき}は{警察署|けいさつしょ}の{{管轄}}だ。", "sentenceTranslationKo": "이 지역은 경찰서의 관할이다." }],
    "轄/直轄": [{ "sentence": "{中央|ちゅうおう}{政府|せいふ}の{{直轄}}{下|か}にある。", "sentenceTranslationKo": "중앙 정부의 직할 하에 있다." }],
    "辰/辰": [{ "sentence": "{今年|ことし}は{{辰}}{年|どし}だ。", "sentenceTranslationKo": "올해는 용띠 해이다." }],
    "辱/屈辱": [{ "sentence": "{試合|しあい}で{{屈辱}}を{味|あじ}わった。", "sentenceTranslationKo": "시합에서 굴욕을 맛봤다." }],
    "辱/辱める": [{ "sentence": "{彼|かれ}を{{辱めて}}はいけない。", "sentenceTranslationKo": "그를 욕보여서는 안 된다." }],
    "辱/侮辱": [{ "sentence": "{相手|あいて}に{{侮辱}}されたと{感|かん}じた。", "sentenceTranslationKo": "상대에게 모욕당했다고 느꼈다." }]
  }
}
