{
  "_comment": "N2 Phase 5-B: 17한자 (般,芸,荒,荷,菓,菜,著,蒸,蔵,薄,虫,血,衣,袋,被,装,裏)",
  "fills": {
    "般": [
      { "readingRef": "ハン", "word": "一般", "wordReading": "いっぱん", "meaningsKo": ["일반"], "examples": [{ "sentence": "{{一般}}{的|てき}な{意見|いけん}を{聞|き}きました。", "sentenceTranslationKo": "일반적인 의견을 들었습니다." }] },
      { "readingRef": "ハン", "word": "全般", "wordReading": "ぜんぱん", "meaningsKo": ["전반"], "examples": [{ "sentence": "{業務|ぎょうむ}の{{全般}}を{担当|たんとう}しています。", "sentenceTranslationKo": "업무 전반을 담당하고 있습니다." }] },
      { "readingRef": "ハン", "word": "諸般", "wordReading": "しょはん", "meaningsKo": ["제반"], "examples": [{ "sentence": "{{諸般}}の{事情|じじょう}で{中止|ちゅうし}になりました。", "sentenceTranslationKo": "제반 사정으로 중지되었습니다." }] }
    ],
    "芸": [
      { "readingRef": "ゲイ", "word": "芸術", "wordReading": "げいじゅつ", "meaningsKo": ["예술"], "examples": [{ "sentence": "{彼女|かのじょ}は{{芸術}}{家|か}を{目指|めざ}しています。", "sentenceTranslationKo": "그녀는 예술가를 목표로 하고 있습니다." }] },
      { "readingRef": "ゲイ", "word": "芸能", "wordReading": "げいのう", "meaningsKo": ["예능"], "examples": [{ "sentence": "{{芸能}}{界|かい}で{活躍|かつやく}しています。", "sentenceTranslationKo": "연예계에서 활약하고 있습니다." }] },
      { "readingRef": "ゲイ", "word": "工芸", "wordReading": "こうげい", "meaningsKo": ["공예"], "examples": [{ "sentence": "{伝統|でんとう}{{工芸}}を{学|まな}んでいます。", "sentenceTranslationKo": "전통 공예를 배우고 있습니다." }] },
      { "readingRef": "ゲイ", "word": "芸人", "wordReading": "げいにん", "meaningsKo": ["연예인", "예인"], "examples": [{ "sentence": "{有名|ゆうめい}な{お笑|おわら}い{{芸人}}を{見|み}ました。", "sentenceTranslationKo": "유명한 코미디 예인을 봤습니다." }] }
    ],
    "荒": [
      { "readingRef": "コウ", "word": "荒野", "wordReading": "こうや", "meaningsKo": ["황야"], "examples": [{ "sentence": "{広大|こうだい}な{{荒野}}を{旅|たび}しました。", "sentenceTranslationKo": "광대한 황야를 여행했습니다." }] },
      { "readingRef": "あらい", "word": "荒い", "wordReading": "あらい", "meaningsKo": ["거칠다"], "examples": [{ "sentence": "{波|なみ}が{{荒い}}{日|ひ}は{海|うみ}に{出|で}ません。", "sentenceTranslationKo": "파도가 거친 날은 바다에 나가지 않습니다." }] },
      { "readingRef": "あれる", "word": "荒れる", "wordReading": "あれる", "meaningsKo": ["거칠어지다"], "examples": [{ "sentence": "{冬|ふゆ}は{肌|はだ}が{{荒れる}}{こと|こと}が{多|おお}いです。", "sentenceTranslationKo": "겨울은 피부가 거칠어지는 일이 많습니다." }] },
      { "readingRef": "あらす", "word": "荒らす", "wordReading": "あらす", "meaningsKo": ["황폐화하다"], "examples": [{ "sentence": "{動物|どうぶつ}が{畑|はたけ}を{{荒らす}}{こと|こと}があります。", "sentenceTranslationKo": "동물이 밭을 망치는 일이 있습니다." }] }
    ],
    "荷": [
      { "readingRef": "カ", "word": "出荷", "wordReading": "しゅっか", "meaningsKo": ["출하"], "examples": [{ "sentence": "{新|あたら}しい{商品|しょうひん}が{{出荷}}されました。", "sentenceTranslationKo": "새 상품이 출하되었습니다." }] },
      { "readingRef": "カ", "word": "入荷", "wordReading": "にゅうか", "meaningsKo": ["입하"], "examples": [{ "sentence": "{人気|にんき}{商品|しょうひん}の{{入荷}}{予定|よてい}を{確認|かくにん}しました。", "sentenceTranslationKo": "인기 상품의 입하 예정을 확인했습니다." }] },
      { "readingRef": "に", "word": "荷物", "wordReading": "にもつ", "meaningsKo": ["짐"], "examples": [{ "sentence": "{重|おも}い{{荷物}}を{運|はこ}びました。", "sentenceTranslationKo": "무거운 짐을 옮겼습니다." }] },
      { "readingRef": "に", "word": "荷台", "wordReading": "にだい", "meaningsKo": ["짐받이"], "examples": [{ "sentence": "{自転車|じてんしゃ}の{{荷台}}に{箱|はこ}を{乗|の}せました。", "sentenceTranslationKo": "자전거 짐받이에 상자를 실었습니다." }] },
      { "readingRef": "に", "word": "荷造り", "wordReading": "にづくり", "meaningsKo": ["짐꾸리기"], "examples": [{ "sentence": "{引|ひ}っ{越|こ}しの{{荷造り}}が{大変|たいへん}です。", "sentenceTranslationKo": "이사 짐꾸리기가 힘듭니다." }] }
    ],
    "菓": [
      { "readingRef": "カ", "word": "菓子", "wordReading": "かし", "meaningsKo": ["과자"], "examples": [{ "sentence": "お{{菓子}}を{食|た}べすぎました。", "sentenceTranslationKo": "과자를 너무 많이 먹었습니다." }] },
      { "readingRef": "カ", "word": "和菓子", "wordReading": "わがし", "meaningsKo": ["일본 전통 과자"], "examples": [{ "sentence": "お{茶|ちゃ}と{{和菓子}}を{楽|たの}しみました。", "sentenceTranslationKo": "차와 일본 전통 과자를 즐겼습니다." }] },
      { "readingRef": "カ", "word": "洋菓子", "wordReading": "ようがし", "meaningsKo": ["양과자"], "examples": [{ "sentence": "{{洋菓子}}{店|てん}でケーキを{買|か}いました。", "sentenceTranslationKo": "양과자점에서 케이크를 샀습니다." }] },
      { "readingRef": "カ", "word": "製菓", "wordReading": "せいか", "meaningsKo": ["제과"], "examples": [{ "sentence": "{彼|かれ}は{{製菓}}{学校|がっこう}に{通|かよ}っています。", "sentenceTranslationKo": "그는 제과 학교에 다니고 있습니다." }] }
    ],
    "菜": [
      { "readingRef": "サイ", "word": "野菜", "wordReading": "やさい", "meaningsKo": ["채소"], "examples": [{ "sentence": "{毎日|まいにち}{{野菜}}を{食|た}べる{ように|ように}しています。", "sentenceTranslationKo": "매일 채소를 먹으려고 하고 있습니다." }] },
      { "readingRef": "サイ", "word": "山菜", "wordReading": "さんさい", "meaningsKo": ["산나물"], "examples": [{ "sentence": "{春|はる}に{{山菜}}を{採|と}りに{行|い}きました。", "sentenceTranslationKo": "봄에 산나물을 캐러 갔습니다." }] },
      { "readingRef": "な", "word": "白菜", "wordReading": "はくさい", "meaningsKo": ["배추"], "examples": [{ "sentence": "{{白菜}}を{使|つか}って{鍋|なべ}を{作|つく}りました。", "sentenceTranslationKo": "배추를 사용해서 전골을 만들었습니다." }] },
      { "readingRef": "サイ", "word": "前菜", "wordReading": "ぜんさい", "meaningsKo": ["전채"], "examples": [{ "sentence": "レストランで{{前菜}}から{始|はじ}まりました。", "sentenceTranslationKo": "레스토랑에서 전채부터 시작되었습니다." }] }
    ],
    "著": [
      { "readingRef": "チョ", "word": "著者", "wordReading": "ちょしゃ", "meaningsKo": ["저자"], "examples": [{ "sentence": "この{本|ほん}の{{著者}}は{有名|ゆうめい}です。", "sentenceTranslationKo": "이 책의 저자는 유명합니다." }] },
      { "readingRef": "チョ", "word": "著作", "wordReading": "ちょさく", "meaningsKo": ["저작"], "examples": [{ "sentence": "{{著作}}{権|けん}を{守|まも}りましょう。", "sentenceTranslationKo": "저작권을 지킵시다." }] },
      { "readingRef": "チョ", "word": "著名", "wordReading": "ちょめい", "meaningsKo": ["저명"], "examples": [{ "sentence": "{{著名}}な{学者|がくしゃ}の{講演|こうえん}を{聞|き}きました。", "sentenceTranslationKo": "저명한 학자의 강연을 들었습니다." }] },
      { "readingRef": "あらわす", "word": "著す", "wordReading": "あらわす", "meaningsKo": ["저술하다"], "examples": [{ "sentence": "{彼|かれ}は{多|おお}くの{本|ほん}を{{著す}}{学者|がくしゃ}です。", "sentenceTranslationKo": "그는 많은 책을 저술하는 학자입니다." }] },
      { "readingRef": "いちじるしい", "word": "著しい", "wordReading": "いちじるしい", "meaningsKo": ["현저하다"], "examples": [{ "sentence": "{進歩|しんぽ}が{{著しい}}{若手|わかて}{選手|せんしゅ}です。", "sentenceTranslationKo": "진보가 현저한 신인 선수입니다." }] }
    ],
    "蒸": [
      { "readingRef": "ジョウ", "word": "蒸気", "wordReading": "じょうき", "meaningsKo": ["증기"], "examples": [{ "sentence": "{昔|むかし}は{{蒸気}}{機関車|きかんしゃ}が{走|はし}っていました。", "sentenceTranslationKo": "옛날에는 증기기관차가 달리고 있었습니다." }] },
      { "readingRef": "ジョウ", "word": "蒸発", "wordReading": "じょうはつ", "meaningsKo": ["증발"], "examples": [{ "sentence": "{暑|あつ}い{日|ひ}は{水分|すいぶん}が{{蒸発}}しやすいです。", "sentenceTranslationKo": "더운 날은 수분이 증발하기 쉽습니다." }] },
      { "readingRef": "むす", "word": "蒸す", "wordReading": "むす", "meaningsKo": ["찌다"], "examples": [{ "sentence": "{饅頭|まんじゅう}を{{蒸す}}{時間|じかん}が{大切|たいせつ}です。", "sentenceTranslationKo": "만두를 찌는 시간이 중요합니다." }] },
      { "readingRef": "むれる", "word": "蒸れる", "wordReading": "むれる", "meaningsKo": ["찌다", "후끈해지다"], "examples": [{ "sentence": "{靴|くつ}の{中|なか}が{{蒸れる}}{ことが|ことが}あります。", "sentenceTranslationKo": "신발 안이 후끈해지는 일이 있습니다." }] }
    ],
    "蔵": [
      { "readingRef": "ゾウ", "word": "冷蔵", "wordReading": "れいぞう", "meaningsKo": ["냉장"], "examples": [{ "sentence": "{食品|しょくひん}を{{冷蔵}}{保存|ほぞん}しました。", "sentenceTranslationKo": "식품을 냉장 보관했습니다." }] },
      { "readingRef": "ゾウ", "word": "貯蔵", "wordReading": "ちょぞう", "meaningsKo": ["저장"], "examples": [{ "sentence": "{食料|しょくりょう}を{{貯蔵}}{庫|こ}に{入|い}れました。", "sentenceTranslationKo": "식량을 저장고에 넣었습니다." }] },
      { "readingRef": "ゾウ", "word": "蔵書", "wordReading": "ぞうしょ", "meaningsKo": ["장서"], "examples": [{ "sentence": "{祖父|そふ}の{{蔵書}}は{多|おお}いです。", "sentenceTranslationKo": "할아버지의 장서는 많습니다." }] },
      { "readingRef": "くら", "word": "蔵", "wordReading": "くら", "meaningsKo": ["창고"], "examples": [{ "sentence": "{古|ふる}い{家|いえ}に{{蔵}}があります。", "sentenceTranslationKo": "오래된 집에 창고가 있습니다." }] }
    ],
    "薄": [
      { "readingRef": "ハク", "word": "希薄", "wordReading": "きはく", "meaningsKo": ["희박"], "examples": [{ "sentence": "{高山|こうざん}では{空気|くうき}が{{希薄}}です。", "sentenceTranslationKo": "고산에서는 공기가 희박합니다." }] },
      { "readingRef": "うすい", "word": "薄い", "wordReading": "うすい", "meaningsKo": ["얇다", "연하다"], "examples": [{ "sentence": "この{紙|かみ}は{{薄い}}です。", "sentenceTranslationKo": "이 종이는 얇습니다." }] },
      { "readingRef": "うすめる", "word": "薄める", "wordReading": "うすめる", "meaningsKo": ["연하게 하다"], "examples": [{ "sentence": "ジュースを{水|みず}で{{薄める}}{こと|こと}にしました。", "sentenceTranslationKo": "주스를 물로 연하게 하기로 했습니다." }] },
      { "readingRef": "うすれる", "word": "薄れる", "wordReading": "うすれる", "meaningsKo": ["옅어지다"], "examples": [{ "sentence": "{記憶|きおく}が{{薄れる}}{時間|じかん}が{経|た}ちました。", "sentenceTranslationKo": "기억이 옅어지는 시간이 흘렀습니다." }] }
    ],
    "虫": [
      { "readingRef": "チュウ", "word": "昆虫", "wordReading": "こんちゅう", "meaningsKo": ["곤충"], "examples": [{ "sentence": "{息子|むすこ}は{{昆虫}}が{大好|だいす}きです。", "sentenceTranslationKo": "아들은 곤충을 매우 좋아합니다." }] },
      { "readingRef": "チュウ", "word": "害虫", "wordReading": "がいちゅう", "meaningsKo": ["해충"], "examples": [{ "sentence": "{農薬|のうやく}で{{害虫}}を{駆除|くじょ}しました。", "sentenceTranslationKo": "농약으로 해충을 구제했습니다." }] },
      { "readingRef": "むし", "word": "虫", "wordReading": "むし", "meaningsKo": ["벌레"], "examples": [{ "sentence": "{庭|にわ}に{きれい|きれい}な{{虫}}がいました。", "sentenceTranslationKo": "정원에 예쁜 벌레가 있었습니다." }] },
      { "readingRef": "むし", "word": "虫歯", "wordReading": "むしば", "meaningsKo": ["충치"], "examples": [{ "sentence": "{甘|あま}い{物|もの}を{食|た}べると{{虫歯}}になります。", "sentenceTranslationKo": "단것을 먹으면 충치가 생깁니다." }] }
    ],
    "血": [
      { "readingRef": "ケツ", "word": "血液", "wordReading": "けつえき", "meaningsKo": ["혈액"], "examples": [{ "sentence": "{病院|びょういん}で{{血液}}{検査|けんさ}を{受|う}けました。", "sentenceTranslationKo": "병원에서 혈액 검사를 받았습니다." }] },
      { "readingRef": "ケツ", "word": "血圧", "wordReading": "けつあつ", "meaningsKo": ["혈압"], "examples": [{ "sentence": "{毎朝|まいあさ}{{血圧}}を{測|はか}っています。", "sentenceTranslationKo": "매일 아침 혈압을 재고 있습니다." }] },
      { "readingRef": "ケツ", "word": "出血", "wordReading": "しゅっけつ", "meaningsKo": ["출혈"], "examples": [{ "sentence": "{怪我|けが}で{{出血}}してしまいました。", "sentenceTranslationKo": "다쳐서 출혈했습니다." }] },
      { "readingRef": "ち", "word": "血", "wordReading": "ち", "meaningsKo": ["피"], "examples": [{ "sentence": "{指|ゆび}を{切|き}って{{血}}が{出|で}ました。", "sentenceTranslationKo": "손가락을 베어 피가 났습니다." }] }
    ],
    "衣": [
      { "readingRef": "イ", "word": "衣服", "wordReading": "いふく", "meaningsKo": ["의복"], "examples": [{ "sentence": "{季節|きせつ}に{合|あ}った{{衣服}}を{選|えら}びます。", "sentenceTranslationKo": "계절에 맞는 의복을 고릅니다." }] },
      { "readingRef": "イ", "word": "衣類", "wordReading": "いるい", "meaningsKo": ["의류"], "examples": [{ "sentence": "{{衣類}}を{回収|かいしゅう}{箱|ばこ}に{入|い}れました。", "sentenceTranslationKo": "의류를 수거함에 넣었습니다." }] },
      { "readingRef": "イ", "word": "衣装", "wordReading": "いしょう", "meaningsKo": ["의상"], "examples": [{ "sentence": "{舞台|ぶたい}の{{衣装}}を{準備|じゅんび}しました。", "sentenceTranslationKo": "무대 의상을 준비했습니다." }] },
      { "readingRef": "ころも", "word": "衣", "wordReading": "ころも", "meaningsKo": ["옷"], "examples": [{ "sentence": "お{坊|ぼう}さんが{{衣}}を{着|き}ています。", "sentenceTranslationKo": "스님이 옷을 입고 있습니다." }] }
    ],
    "袋": [
      { "readingRef": "タイ", "word": "風袋", "wordReading": "ふうたい", "meaningsKo": ["풍대"], "examples": [{ "sentence": "{{風袋}}{抜|ぬ}きで{重|おも}さを{量|はか}りました。", "sentenceTranslationKo": "풍대 빼고 무게를 잤습니다." }] },
      { "readingRef": "ふくろ", "word": "袋", "wordReading": "ふくろ", "meaningsKo": ["봉지", "주머니"], "examples": [{ "sentence": "スーパーで{{袋}}を{有料|ゆうりょう}にしました。", "sentenceTranslationKo": "슈퍼에서 봉지를 유료화했습니다." }] },
      { "readingRef": "ふくろ", "word": "手袋", "wordReading": "てぶくろ", "meaningsKo": ["장갑"], "examples": [{ "sentence": "{冬|ふゆ}は{暖|あたた}かい{{手袋}}が{必要|ひつよう}です。", "sentenceTranslationKo": "겨울은 따뜻한 장갑이 필요합니다." }] },
      { "readingRef": "ふくろ", "word": "紙袋", "wordReading": "かみぶくろ", "meaningsKo": ["종이봉투"], "examples": [{ "sentence": "{買|か}い{物|もの}を{{紙袋}}に{入|い}れました。", "sentenceTranslationKo": "쇼핑한 것을 종이봉투에 담았습니다." }] },
      { "readingRef": "ふくろ", "word": "福袋", "wordReading": "ふくぶくろ", "meaningsKo": ["복주머니"], "examples": [{ "sentence": "お{正月|しょうがつ}に{{福袋}}を{買|か}いました。", "sentenceTranslationKo": "정월에 복주머니를 샀습니다." }] }
    ],
    "被": [
      { "readingRef": "ヒ", "word": "被害", "wordReading": "ひがい", "meaningsKo": ["피해"], "examples": [{ "sentence": "{台風|たいふう}で{大|おお}きな{{被害}}が{出|で}ました。", "sentenceTranslationKo": "태풍으로 큰 피해가 났습니다." }] },
      { "readingRef": "ヒ", "word": "被災", "wordReading": "ひさい", "meaningsKo": ["피재", "재해를 당함"], "examples": [{ "sentence": "{地震|じしん}の{{被災}}{者|しゃ}を{支援|しえん}しました。", "sentenceTranslationKo": "지진의 피재자를 지원했습니다." }] },
      { "readingRef": "かぶる", "word": "被る", "wordReading": "かぶる", "meaningsKo": ["쓰다", "뒤집어쓰다"], "examples": [{ "sentence": "{暑|あつ}いので{帽子|ぼうし}を{{被る}}{ように|ように}しました。", "sentenceTranslationKo": "더워서 모자를 쓰도록 했습니다." }] },
      { "readingRef": "ヒ", "word": "被告", "wordReading": "ひこく", "meaningsKo": ["피고"], "examples": [{ "sentence": "{裁判|さいばん}で{{被告}}が{弁明|べんめい}しました。", "sentenceTranslationKo": "재판에서 피고가 변명했습니다." }] }
    ],
    "装": [
      { "readingRef": "ソウ", "word": "服装", "wordReading": "ふくそう", "meaningsKo": ["복장"], "examples": [{ "sentence": "{面接|めんせつ}には{{服装}}に{気|き}をつけてください。", "sentenceTranslationKo": "면접에는 복장에 신경 써 주세요." }] },
      { "readingRef": "ソウ", "word": "装置", "wordReading": "そうち", "meaningsKo": ["장치"], "examples": [{ "sentence": "{新|あたら}しい{{装置}}を{設置|せっち}しました。", "sentenceTranslationKo": "새 장치를 설치했습니다." }] },
      { "readingRef": "ソウ", "word": "装飾", "wordReading": "そうしょく", "meaningsKo": ["장식"], "examples": [{ "sentence": "クリスマスの{{装飾}}を{飾|かざ}りました。", "sentenceTranslationKo": "크리스마스 장식을 했습니다." }] },
      { "readingRef": "ソウ", "word": "包装", "wordReading": "ほうそう", "meaningsKo": ["포장"], "examples": [{ "sentence": "プレゼントの{{包装}}を{頼|たの}みました。", "sentenceTranslationKo": "선물 포장을 부탁했습니다." }] },
      { "readingRef": "よそおう", "word": "装う", "wordReading": "よそおう", "meaningsKo": ["꾸미다", "차려입다"], "examples": [{ "sentence": "{結婚式|けっこんしき}のために{きれい|きれい}に{{装う}}つもりです。", "sentenceTranslationKo": "결혼식을 위해 예쁘게 차려입을 작정입니다." }] }
    ],
    "裏": [
      { "readingRef": "リ", "word": "裏面", "wordReading": "りめん", "meaningsKo": ["이면"], "examples": [{ "sentence": "コインの{{裏面}}に{年号|ねんごう}が{書|か}いてあります。", "sentenceTranslationKo": "동전의 이면에 연호가 적혀 있습니다." }] },
      { "readingRef": "うら", "word": "裏", "wordReading": "うら", "meaningsKo": ["뒤", "안쪽"], "examples": [{ "sentence": "{家|いえ}の{{裏}}に{庭|にわ}があります。", "sentenceTranslationKo": "집 뒤에 정원이 있습니다." }] },
      { "readingRef": "うら", "word": "裏口", "wordReading": "うらぐち", "meaningsKo": ["뒷문"], "examples": [{ "sentence": "{店|みせ}の{{裏口}}から{出|で}ました。", "sentenceTranslationKo": "가게 뒷문으로 나갔습니다." }] },
      { "readingRef": "うら", "word": "裏切る", "wordReading": "うらぎる", "meaningsKo": ["배신하다"], "examples": [{ "sentence": "{友|とも}だちを{{裏切る}}{こと|こと}はできません。", "sentenceTranslationKo": "친구를 배신할 수는 없습니다." }] },
      { "readingRef": "うら", "word": "裏庭", "wordReading": "うらにわ", "meaningsKo": ["뒤뜰"], "examples": [{ "sentence": "{{裏庭}}に{花|はな}を{植|う}えました。", "sentenceTranslationKo": "뒤뜰에 꽃을 심었습니다." }] }
    ]
  }
}
